README.md
setup.py
coolered/__init__.py
coolered.egg-info/PKG-INFO
coolered.egg-info/SOURCES.txt
coolered.egg-info/dependency_links.txt
coolered.egg-info/entry_points.txt
coolered.egg-info/requires.txt
coolered.egg-info/top_level.txt