Metadata-Version: 1.1
Name: coolered
Version: 0.1.0
Summary: A better dslackw/colored
Home-page: https://github.com/llamicron/coolered
Author: Luke Sweeney
Author-email: llamicron@gmail.com
License: UNKNOWN
Keywords: development color terminal text codes ascii colored coolered color-terminal
Platform: UNKNOWN
Classifier: Development Status :: 1 - Planning
Classifier: Intended Audience :: Developers
Classifier: Topic :: Software Development :: Documentation
Classifier: Topic :: Software Development
Classifier: License :: OSI Approved :: MIT License
Classifier: Programming Language :: Python :: 3
Classifier: Programming Language :: Python :: 3.4
Classifier: Programming Language :: Python :: 3.5
Classifier: Programming Language :: Python :: 3.6
